JquiApiDoc/README.md
JquiApiDoc/__init__.py
JquiApiDoc/__main__.py
JquiApiDoc/file.epub
JquiApiDoc/index.html
JquiApiDoc/css/__init__.py
JquiApiDoc/css/annotations.css
JquiApiDoc/css/main.css
JquiApiDoc/css/normalize.css
JquiApiDoc/css/popup.css
JquiApiDoc/font/__init__.py
JquiApiDoc/font/fontello.eot
JquiApiDoc/font/fontello.svg
JquiApiDoc/font/fontello.ttf
JquiApiDoc/font/fontello.woff
JquiApiDoc/img/__init__.py
JquiApiDoc/img/annotator-glyph-sprite.png
JquiApiDoc/img/annotator-icon-sprite.png
JquiApiDoc/img/apple-touch-icon.png
JquiApiDoc/img/cancelfullscreen.png
JquiApiDoc/img/close.png
JquiApiDoc/img/fullscreen.png
JquiApiDoc/img/loader.gif
JquiApiDoc/img/menu-icon.png
JquiApiDoc/img/save.png
JquiApiDoc/img/saved.png
JquiApiDoc/img/settings-s.png
JquiApiDoc/img/settings.png
JquiApiDoc/img/star.png
JquiApiDoc/js/__init__.py
JquiApiDoc/js/epub.js
JquiApiDoc/js/epub.min.js
JquiApiDoc/js/epub.min.map
JquiApiDoc/js/hooks.min.js
JquiApiDoc/js/hooks.min.map
JquiApiDoc/js/reader.js
JquiApiDoc/js/reader.js.map
JquiApiDoc/js/reader.min.js
JquiApiDoc/js/reader.min.map
JquiApiDoc/js/hooks/__init__.py
JquiApiDoc/js/hooks/extensions/__init__.py
JquiApiDoc/js/hooks/extensions/highlight.js
JquiApiDoc/js/libs/__init__.py
JquiApiDoc/js/libs/jquery.min.js
JquiApiDoc/js/libs/localforage.min.js
JquiApiDoc/js/libs/screenfull.js
JquiApiDoc/js/libs/screenfull.min.js
JquiApiDoc/js/libs/zip.min.js
JquiApiDoc/js/plugins/__init__.py
JquiApiDoc/js/plugins/hypothesis.js
JquiApiDoc/js/plugins/search.js
jqui_api_doc-2024.3.1.0.dist-info/METADATA
jqui_api_doc-2024.3.1.0.dist-info/WHEEL
jqui_api_doc-2024.3.1.0.dist-info/entry_points.txt
jqui_api_doc-2024.3.1.0.dist-info/top_level.txt
jqui_api_doc-2024.3.1.0.dist-info/RECORD
